AUTHORS
ChangeLog
README.rst
requirements.txt
setup.cfg
setup.py
api_mask/__init__.py
api_mask/models.py
api_mask/overrides.py
api_mask/urls.py
api_mask/api_access/__init__.py
api_mask/api_access/urls.py
api_mask/api_access/views.py
api_mask/templatetags/__init__.py
api_mask/templatetags/mask.py
horizon_api_mask.egg-info/PKG-INFO
horizon_api_mask.egg-info/SOURCES.txt
horizon_api_mask.egg-info/dependency_links.txt
horizon_api_mask.egg-info/not-zip-safe
horizon_api_mask.egg-info/pbr.json
horizon_api_mask.egg-info/requires.txt
horizon_api_mask.egg-info/top_level.txt